{
  "success": true,
  "data": {
    "topicList": [
      {
        "id": 1,
        "title": "社会热点",
        "imgUrl": "https://upload.jianshu.io/users/upload_avatars/9988193/fc26c109-1ae6-4327-a298-2def343e9cd8.jpg?imageMogr2/auto-orient/strip|imageView2/1/w/96/h/96/format/webp"
      },
      {
        "id": 2,
        "title": "手绘作品",
        "imgUrl": "https://upload.jianshu.io/users/upload_avatars/3950651/acfaa0ce-42fe-424a-b7c8-9a0136fb96ec.jpg?imageMogr2/auto-orient/strip|imageView2/1/w/96/h/96/format/webp"
      }
    ],
    "articleList": [
      {"title":"纯洁的男女关系","":"","imgUrl":"","abstract":"深夜，一对年轻男女来到一家宾馆。 “开两个单间！”男的拿着身份证说。 “不好意思，现在房间住满了，只剩一个标准间了。”前台小姐说。 男的看了一眼...","meta":"78.6","author":"金错刀618","meta2":"229","meta3":"1490"},
      {"title":"《让岁月变成诗》名人语录","":"","imgUrl":"https://upload-images.jianshu.io/upload_images/15684874-ffc8c037e5f10911.jpg?imageMogr2/auto-orient/strip|imageView2/1/w/180/h/120","abstract":"梁实秋说：你走，我不送你。你来，无论多大风多大雨，我要去接你。 海明威说：优于别人，并不高贵，真正的高贵应该是优于过去的自己。 顾漫说：一个笑就...","meta":"44","author":"时惠","meta2":"11","meta3":""},
      {"title":"“因为10个口罩，我看到了妻子的另一面，终止了两年的婚外恋”","":"","imgUrl":"https://upload-images.jianshu.io/upload_images/11864358-622c38825ebb854e.jpg?imageMogr2/auto-orient/strip|imageView2/1/w/180/h/120","abstract":"01 作家詹迪·尼尔森曾说：“遇见灵魂伴侣的感觉，就好像是走进一座你曾经住过的房子里——你认识那些家具，认识墙上的画，架上的书，抽屉里的东西：如...","meta":"179.2","author":"灵双儿","meta2":"159","meta3":"1071"},
      {"title":"细读《挪威的森林》","":"","imgUrl":"https://upload-images.jianshu.io/upload_images/15517692-7a1b517edb1eff6d.jpg?imageMogr2/auto-orient/strip|imageView2/1/w/180/h/120","abstract":"《挪威的森林》，村上春树的代表作。因它的名气特别响亮，特定网购了一本，放在书架上放好几个月了，最近才有时间打开阅读。 花了六天时间读完，基本上是...","meta":"8.5","author":"MR_TS","meta2":"27","meta3":"149"},
      {"title":"“宅家35天后，离婚人数激增”：一场疫情，考验了多少人的婚姻","":"","imgUrl":"https://upload-images.jianshu.io/upload_images/1202579-a96c50c56723acf3?imageMogr2/auto-orient/strip|imageView2/1/w/360/h/240","abstract":"今天是精读君陪伴你终身成长的第2342天 1 上周末，朋友深夜找我哭诉。 电话那头，她一边抹着眼泪，一边坚定地跟我说“疫情结束后，马上离婚。” ...","meta":"55.6","author":"精读君","meta2":"32","meta3":"300"},
      {"title":"疫情结束了，我想去离婚","":"","imgUrl":"https://upload-images.jianshu.io/upload_images/8357505-951bf44017330232.jpg?imageMogr2/auto-orient/strip|imageView2/1/w/180/h/120","abstract":"晚上闺蜜发来消息，说过了疫情，要去办离婚手续，这回彻底心凉了。 闺蜜两口子都是事业单位职工，两人有个儿子今年上高一，日子一直过得安宁舒适，至少外...","meta":"281.4","author":"风中的糯米","meta2":"615","meta3":"1405"},
      {"title":"丈夫和媳妇说，把游戏关了，我们来大战三百回合","":"","imgUrl":"","abstract":"下班回到家，媳妇儿正在坐在电脑前玩LOL，幽暗的灯光下一副岁月静好的样子。 我兽性大发扑了过去抱住她的腰:“把游戏关了，我们来大战三百回合吧。”...","meta":"42.0","author":"麦田大豆","meta2":"96","meta3":"622"},
      {"title":"两瓶饮料","":"","imgUrl":"","abstract":"父亲常年在外地打工，有一次，父亲回家，特意给儿子带了礼物，是两瓶饮料。儿子迫不及待地拧开瓶盖，咕咚就一大口。 父亲赶紧问，好喝吗？儿子嘴里还含着...","meta":"19.1","author":"麦田大豆","meta2":"71","meta3":"258"},
      {"title":"无声的炫耀","":"","imgUrl":"","abstract":"邻居家女儿远嫁外地，本来这件事情，就让邻居很生气，可是无奈女儿喜欢呀，他们两口子也犟不过，就答应了。 结婚以后，生了个女儿，四年后又生了个女儿，...","meta":"25.0","author":"四点工作室","meta2":"46","meta3":"233"},
      {"title":"敬畏自然1","":"","imgUrl":"https://upload-images.jianshu.io/upload_images/10666569-dc8b62578468db31.jpg?imageMogr2/auto-orient/strip|imageView2/1/w/180/h/120","abstract":"武汉新型冠状病毒产生的疫情牵动着全国每一个家庭，让整个国家陷入一场危~难之中。 新型病毒到底来源于何方，目前尚不能盖~棺定论，不过野生动物携带这...","meta":"141.4","author":"放下皆得","meta2":"151","meta3":"670"},
      {"title":"上班第一天","":"","imgUrl":"https://upload-images.jianshu.io/upload_images/14805474-d0c2e5243e2c9d41.jpg?imageMogr2/auto-orient/strip|imageView2/1/w/180/h/120","abstract":"年前买了40个口罩觉得很多，过年才发现家人都没买上，于是给婆婆10个，爸妈10个，弟弟家10个，女儿抱怨：都送人了咱家没了！我安慰她咱再买！ 今...","meta":"86.3","author":"洋木","meta2":"115","meta3":"712"},
      {"title":"疫情赋闲，让老公变了","":"","imgUrl":"","abstract":"昨天晚上快10点了，忽然发现微信一条信息，点开一看，是老公发来的，就俩字：媳妇。我有点意外，老公从来没这样叫过我，今天这是怎么啦？我忙问：这是什...","meta":"66.2","author":"风中的糯米","meta2":"147","meta3":"1125"},
      {"title":"“宅家35天后，离婚人数激增”：一场疫情，考验了多少人的婚姻","":"","imgUrl":"https://upload-images.jianshu.io/upload_images/1202579-a96c50c56723acf3?imageMogr2/auto-orient/strip|imageView2/1/w/180/h/120","abstract":"今天是精读君陪伴你终身成长的第2342天 1 上周末，朋友深夜找我哭诉。 电话那头，她一边抹着眼泪，一边坚定地跟我说“疫情结束后，马上离婚。” ...","meta":"55.6","author":"精读君","meta2":"32","meta3":"300"},
      {"title":"低情商的十个可能的表现","":"","imgUrl":"","abstract":"1. 不懂得基本的社交礼仪 总是喜欢随意地麻烦别人，最经典而又普遍的案例就是：群发求赞、群发测试清理好友（这个行为不仅情商低，智商也低）、没有交...","meta":"49.7","author":"水之心","meta2":"70","meta3":"750"},
      {"title":"李嘉欣与8岁儿子共浴，当亲情越过界限，对孩子更多的是“伤害”","":"","imgUrl":"https://upload-images.jianshu.io/upload_images/11864358-2c5f48f03dffb247.jpg?imageMogr2/auto-orient/strip|imageView2/1/w/180/h/120","abstract":"父母永远都是孩子最亲近的人，特别是妈妈从怀孕到生孩子这个过程，她们给了孩子生命，同时也时刻守护着孩子们的成长。 绝大多数情况下，妈妈和孩子都是最...","meta":"28.2","author":"灵双儿","meta2":"124","meta3":"638"},
      {"title":"一个人是否值得交往，看这四点就够了","":"","imgUrl":"","abstract":"有人说：“不必把太多人请进生命里，若他们走进不了你的内心，就只会把你的生命搅扰得拥挤不堪。” 朋友不必多，贵在能知心。珍贵的情谊，要留给最值得结...","meta":"36.9","author":"一气浩然","meta2":"44","meta3":"328"},
      {"title":"与公婆同住的日子，就像在房子里安装了360无死角摄像头！","":"","imgUrl":"","abstract":"因为这次疫情，公婆回不去，所以，就开启了同住的日子。 因为他们的存在，我在自己的家里，感到非常不自在。 我吃饭吃得慢，公公就一个劲在婆婆面前唠叨...","meta":"132.9","author":"这世间的美好唯你而已","meta2":"121","meta3":"228"},
      {"title":"检验婚姻最好的标准:睡觉!","":"","imgUrl":"https://upload-images.jianshu.io/upload_images/20247732-0fd53b6770ac1e6d.jpg?imageMogr2/auto-orient/strip|imageView2/1/w/180/h/120","abstract":"有人说： “真正的爱情不是海誓山盟，而是潜藏在细枝末节的小事中。” 的确，很多时候，从日常生活的细节，就能看出一段感情是否美满，一段婚姻是否能够...","meta":"21.7","author":"知心之友","meta2":"42","meta3":"201"},
      {"title":"47岁的陶虹：绝顶聪明的女人，都不声不响地拥有了全世界","":"","imgUrl":"https://upload-images.jianshu.io/upload_images/18529253-0b13112a1b1068ba?imageMogr2/auto-orient/strip|imageView2/1/w/150/h/120","abstract":"文 | 嘻嘻 ​ 最近，随着《小欢喜》开播，已经很久没在电视剧荧幕里出现的陶虹，重新回到了大众的视野中。 剧中的她，饰演一位金牌辅导老师。刚出场...","meta":"1079","author":"铁成武","meta2":"71","meta3":""},
      {"title":"杨紫甜到炸的“新恋情”：男友上亿身家，宠妻人设开启，千万少女求嫁","":"","imgUrl":"https://upload-images.jianshu.io/upload_images/15491776-f03763d7feb3d381?imageMogr2/auto-orient/strip|imageView2/1/w/150/h/120","abstract":"最近，到处都是“李现”这个名字。 看过那么多青春偶像剧，像《亲爱的热爱的》这么“上头”的，还真是独一份。 一个“李现 7月男友”的话题在微博热搜...","meta":"117.8","author":"走着瞧旅行","meta2":"66","meta3":"606"},
      {"title":"终于找到杨紫演什么火什么，ab演什么扑什么的原因","":"","imgUrl":"https://upload-images.jianshu.io/upload_images/3900546-b615039760ab5587?imageMogr2/auto-orient/strip|imageView2/1/w/150/h/120","abstract":"要问谁是今年新晋的锦鲤女神，那肯定非杨紫莫属。 有她在的地方，先是火了《亲爱的，热爱的》，“现男友”成为七月爆款。 后来的《中餐厅》也一改前几季...","meta":"111.1","author":"花痴女王","meta2":"103","meta3":"791"},
      {"title":"谢娜被何炅排挤疏远：活得太自我的人，下场都很惨","":"","imgUrl":"","abstract":"最近看《快乐大本营》，发现谢娜和快乐家族其他成员的气氛非常微妙。 尤其是在最新的这一期节目里，无论是何炅、维嘉，抑或是吴昕海涛，在节目互动的时候...","meta":"1473","author":"S小姐说","meta2":"221","meta3":"2"},
      {"title":"她48岁学画，一年就办个人画展！专家：没艺术价值，是农妇乱涂鸦","":"","imgUrl":"https://upload-images.jianshu.io/upload_images/4741933-77158752df1b1c2b.jpeg?imageMogr2/auto-orient/strip|imageView2/1/w/150/h/120","abstract":"被网友称为天才画家的她说，一定会像种田一样，去认真对待画画，将画画一直画下去。无论是炒作也好，还是偶然的雷同也罢，因为画画而改变了一位农妇的生活...","meta":"166.4","author":"陈洪标写字说画","meta2":"224","meta3":"838"},
      {"title":"照片拍完之后，他们就死了……","":"","imgUrl":"https://upload-images.jianshu.io/upload_images/18529253-1d826a2bca7ac0bd?imageMogr2/auto-orient/strip|imageView2/1/w/150/h/120","abstract":"照片拍摄的瞬间，一切就定格成为历史。不过下面这组照片中，拍摄者（或被拍摄者）万万不会想到，他们的人生会这样快地走向终结： 挑战者号航天飞机的成员...","meta":"390","author":"铁成武","meta2":"45","meta3":""},
      {"title":"开发部署提速8倍！这款IDE插件了解一下？","":"","imgUrl":"https://upload-images.jianshu.io/upload_images/13492518-597e6b756729cc18.jpeg?imageMogr2/auto-orient/strip|imageView2/1/w/150/h/120","abstract":"对于开发者而言，提高工作效率大概有 2 种主要方式，第一种方式就是加快自己的工作速度，争取在同一段时间内多码一些代码、多干一些活来实现多产；而聪...","meta":"18.8","author":"阿里云官网","meta2":"4","meta3":"79"},
      {"title":"怀孕女子大巴上假装肚子疼，逼迫司机半路停车，却救回一车人性命","":"","imgUrl":"","abstract":"在一个长途大巴上，怀孕女子马晓晴突然大喊肚子疼，要下车方便一下。司机不同意，在马晓晴的逼迫下，不得已将车停在了路边。司机骂骂咧咧，但出人意料的是...","meta":"216.3","author":"猫哥聊社会","meta2":"163","meta3":"1609"},
      {"title":"为上幼儿园陪睡校长：不惜碾碎身体给孩子铺路，值吗？","":"","imgUrl":"https://upload-images.jianshu.io/upload_images/1503442-966563dfbb60725c?imageMogr2/auto-orient/strip|imageView2/1/w/150/h/120","abstract":"来源：三点一弯钩 作者：芒来小姐 01 最近网上曝出一个很魔幻的新闻：母亲为了孩子能读高质量的私立幼儿园，陪睡校长。 这组截图刷屏了我的朋友圈，...","meta":"316.1","author":"芒来小姐","meta2":"783","meta3":"2684"},
      {"title":"做了这么久的程序员，你知道为什么会有Lambda表达式吗？","":"","imgUrl":"https://upload-images.jianshu.io/upload_images/15590149-c541bc6f667b8ac4?imageMogr2/auto-orient/strip|imageView2/1/w/150/h/120","abstract":"享学课堂特邀作者：老顾转载请声明出处！ 前言 Java8有一些新的特性，今天老顾给大家分享一下关于Lambda表达式的由来，一开始感觉Lambd...","meta":"43.1","author":"享学课堂","meta2":"26","meta3":"184"},
      {"title":"Flutter - 登录动画","":"","imgUrl":"https://upload-images.jianshu.io/upload_images/17203299-7917effb8470748f.png?imageMogr2/auto-orient/strip|imageView2/1/w/150/h/120","abstract":"在Flutter应用程序中实现超级流畅的动画 在这篇文章中，我将带您完成在Flutter应用程序中实现流畅动画的步骤。 时间线 这是一个时间轴，...","meta":"19.1","author":"开心人开发世界","meta2":"9","meta3":"141"},
      {"title":"看！闲鱼又开源了一个 Flutter 开发利器","":"","imgUrl":"https://upload-images.jianshu.io/upload_images/2509688-5bd44d55ff3fe90d.png?imageMogr2/auto-orient/strip|imageView2/1/w/150/h/120","abstract":"阿里妹导读：随着 Flutter 这一框架的快速发展，有越来越多的业务开始使用 Flutter 来重构或新建其产品。但在我们的实践过程中发现，一...","meta":"15.2","author":"阿里云云栖号","meta2":"5","meta3":"98"},
      {"title":"17种会让你变开心的生活习惯","":"","imgUrl":"https://upload-images.jianshu.io/upload_images/2425636-9b5676d54f686366.jpg?imageMogr2/auto-orient/strip|imageView2/1/w/150/h/120","abstract":"17种会让你变开心的生活习惯 1.每天拍几张照片 心理学家建议，每天用相机拍下一些身边的人和事，如窗外的树木、路边的小花、邻居家的孩子和朋友的婚...","meta":"5.6","author":"伦小野","meta2":"11","meta3":"52"},
      {"title":"世人皆知：“万恶淫为首”，其实下一句才是精华，道尽人性百态","":"","imgUrl":"https://upload-images.jianshu.io/upload_images/16721915-ab9e01ba6451156c.png?imageMogr2/auto-orient/strip|imageView2/1/w/150/h/120","abstract":"中国有五千多年的深厚文化。许多老话我们都很熟悉。例如，“单身汉的钱多，讨了婆娘烧破锅”“千年王八万年龟，百年兔子不可追”“人穷莫入众，言轻莫劝人...","meta":"185.2","author":"谢一然","meta2":"142","meta3":"1097"},
      {"title":"一文教会你如何写复杂业务代码","":"","imgUrl":"https://upload-images.jianshu.io/upload_images/2509688-b3d0a31ba4c3a1a7.png?imageMogr2/auto-orient/strip|imageView2/1/w/150/h/120","abstract":"了解我的人都知道，我一直在致力于应用架构和代码复杂度的治理。 这两天在看零售通商品域的代码。面对零售通如此复杂的业务场景，如何在架构和代码层面进...","meta":"47.4","author":"阿里云云栖号","meta2":"11","meta3":"309"},
      {"title":"10天3名医生猝死，46岁李冰冰“身体报废”：别再熬夜，真的会死","":"","imgUrl":"https://upload-images.jianshu.io/upload_images/18529253-7c63a3d53e703e52?imageMogr2/auto-orient/strip|imageView2/1/w/150/h/120","abstract":"作者：洞见Fine 人类从不做正确的事，他们总做最有快感的事，然后后悔。 01 世上最可怕的不是悲剧，而是悲剧的重复。 看到一则消息，7月4日，...","meta":"209","author":"铁成武","meta2":"44","meta3":""},
      {"title":"“健身房里是真的很乱吗？”“是的！！”","":"","imgUrl":"","abstract":"健身房，是一个很神奇的存在。 常常听到有人问：健身房真的很乱吗？是的，这里常常有各种“妖怪”出没，五花八门，让人眼花缭乱，下面择其中最让人难以h...","meta":"124.4","author":"极物","meta2":"92","meta3":"649"},
      {"title":"今年必看第一国剧：平庸，才是每个人最终的归宿","":"","imgUrl":"https://upload-images.jianshu.io/upload_images/1897565-6976126618844764?imageMogr2/auto-orient/strip|imageView2/1/w/150/h/120","abstract":"物道君语：8月12日《长安十二时辰》收官了，这部2019年豆瓣评分8.4的神剧让我们亲眼目睹了一次长安美。赶在收官之前，物道君专程跑了趟北京和马...","meta":"39.7","author":"物道","meta2":"7","meta3":"208"},
      {"title":"为什么被你们吹爆了的《哪吒》，我只看到了满屏的尴尬？","":"","imgUrl":"https://upload-images.jianshu.io/upload_images/12081621-b05fe51264d22dcb.jpg?imageMogr2/auto-orient/strip|imageView2/1/w/150/h/120","abstract":"昨天我看了个动画片。片子讲的是一个村里有个小孩子自出生起体内就封印了一股强大的妖力，于是村民们把他当做妖怪，畏惧他，疏远他，避之唯恐不及。他表面...","meta":"473.2","author":"雨天_稻草人","meta2":"1992","meta3":"3213"},
      {"title":"徐峥罕见发怒：“让你儿子离我女儿远点。”","":"","imgUrl":"https://upload-images.jianshu.io/upload_images/18529254-51601eb6583e310c?imageMogr2/auto-orient/strip|imageView2/1/w/150/h/120","abstract":"来源 | 水木文摘（ID：mweishijie） 水木君说： 教会孩子保护自己，提高安全意识是父母的必修课。孩子是我们生命的延续，是希望，请尽全...","meta":"553","author":"書酱","meta2":"75","meta3":""},
      {"title":"全球最强卧底：潜入黑帮24年，喊话同事：再不收网老大就是我了","":"","imgUrl":"","abstract":"卧底在警匪电影中几乎都会出现，大家都知道做卧底是非常危险的，一旦暴露必然是被黑恶势力折磨至死，所以这些卧底往往都是需最优秀的警察才能担当，不仅要...","meta":"98","author":"二叁叁叁","meta2":"19","meta3":""},
      {"title":"离婚的马伊琍，不需要心疼","":"","imgUrl":"https://upload-images.jianshu.io/upload_images/1180020-b89102ea4b667a07?imageMogr2/auto-orient/strip|imageView2/1/w/150/h/120","abstract":"7月28日，文章马伊琍相继发出微博，宣布两人已离婚。 从2008年二人结婚，到2014年“且行且珍惜”的风波，11年的婚姻还是以分手告终。 公布...","meta":"91.7","author":"网易公开课","meta2":"71","meta3":"672"},
      {"title":"小团队从0搭建devOPS平台-Prometheus监控报警系统","":"","imgUrl":"https://upload-images.jianshu.io/upload_images/10096448-3864c55c6783f2f5.png?imageMogr2/auto-orient/strip|imageView2/1/w/150/h/120","abstract":"在当前微服务架构流行情况下，对于初创企业，可能就几个技术（2-20个不等），但是却要开发十多个应用，要维护几十台云机器，甚至可能是混合云的模式。...","meta":"48.8","author":"jerry的技术与思维","meta2":"9","meta3":"270"},
      {"title":"张一山喊话杨紫，为什么不让我演韩商言？杨紫的回答暗藏玄机","":"","imgUrl":"https://upload-images.jianshu.io/upload_images/2259045-9348eb9aa7465776?imageMogr2/auto-orient/strip|imageView2/1/w/150/h/120","abstract":"文 | 夏竹麦叔工作室作者 最近《亲爱的》热播， “韩商言”的扮演者李现火的一塌糊涂，剧中李现和杨紫的爱情也让很多人艳羡。 众所周知，张一山和杨...","meta":"224.4","author":"麦大人","meta2":"137","meta3":"882"},
      {"title":"Element-UI中关于table表格的那些骚操作","":"","imgUrl":"https://upload-images.jianshu.io/upload_images/2484592-8b3fe5f2984747a6.jpg?imageMogr2/auto-orient/strip|imageView2/1/w/150/h/120","abstract":"最近的项目中使用到element-ui组件库，由于做的是后台管理系统，所以经常需要操作表格，编辑样式的过程中遇到一些问题，官网针对table给出...","meta":"21.5","author":"视觉派Pie","meta2":"22","meta3":"133"},
      {"title":"同班的章子怡、袁泉都火了，为什么她不行？","":"","imgUrl":"https://upload-images.jianshu.io/upload_images/18529255-35ce82ac4de8ede9?imageMogr2/auto-orient/strip|imageView2/1/w/150/h/120","abstract":"本文来源：视觉志（id：iiidaily） 作者 | 柚子 最近，在电视剧《七月与安生》里看到了曾黎。 来来来，你们随意感受下。 43岁，拥有这...","meta":"178","author":"热心市民顾先生","meta2":"17","meta3":""},
      {"title":"《武林外传》后，闫妮姚晨都走红13年了，这次终于轮到她了吗？","":"","imgUrl":"https://upload-images.jianshu.io/upload_images/18862771-e001e192ce6fb530?imageMogr2/auto-orient/strip|imageView2/1/w/150/h/120","abstract":"文 | 依琳 ​ 看过热播剧《加油，你是最棒的》的朋友，有没有人跟她姐一样，冲着邓伦、马思纯去追剧，没想到被剧中倪虹洁饰演的“牛美丽”圈了粉呢。...","meta":"153","author":"深夜放映室","meta2":"21","meta3":"1"},
      {"title":"在闲鱼上,你能看到全国人民每天都在捡些什么奇葩东西","":"","imgUrl":"https://upload-images.jianshu.io/upload_images/18529258-488e52f53c88ee85?imageMogr2/auto-orient/strip|imageView2/1/w/150/h/120","abstract":"文章来源：跳海大院 每个年轻人出门前，都会受到两个灵魂问题拷问，一个是“我的袜子在哪里”，一个是“我的另一只airpods在哪？” 彷佛两只ai...","meta":"413","author":"二叁叁叁","meta2":"29","meta3":""},
      {"title":"29岁女明星被潜规则后自杀 : 这世上，真的没有捷径","":"","imgUrl":"https://upload-images.jianshu.io/upload_images/18529262-ff9a98379987d94b?imageMogr2/auto-orient/strip|imageView2/1/w/150/h/120","abstract":"0 1 女演员吴可熙，可能大家都不熟悉。 但是说到在2016年台湾金马奖颁奖典礼上，冯小刚宣布最佳女主角的得奖者是周冬雨时，有一女演员翻白眼的，...","meta":"590","author":"键盘就是力量","meta2":"80","meta3":"1"},
      {"title":"孟昌明：人体的诱惑","":"","imgUrl":"https://upload-images.jianshu.io/upload_images/8892910-bb199a58f2846ac7.jpg?imageMogr2/auto-orient/strip|imageView2/1/w/150/h/120","abstract":"气温舒适，老是二十度左右，Oakland没有江南那湿唧唧的夏，我也不喜欢空调，苏州时再热也那么傻乎乎呆着，写字画画刻印章不闲。 这夏天不用空调冬...","meta":"30.9","author":"艺术与艺术家","meta2":"16","meta3":"122"},
      {"title":"最残忍的画家：给活猪纹身，取下猪皮装裱成画，一幅卖100万","":"","imgUrl":"https://upload-images.jianshu.io/upload_images/3651857-81a7cc96dc91c539.jpeg?imageMogr2/auto-orient/strip|imageView2/1/w/150/h/120","abstract":"在京郊顺义某个村庄有一处小小的养猪场，这里养着数十头白白净净的猪，猪场的主人是一个叫威姆·德沃伊的老外。 对于这个老外开办的小小养猪场，附近邻居...","meta":"76.4","author":"有画说艺术","meta2":"140","meta3":"258"},
      {"title":"40岁“宠妻男神”人设崩塌？多少女人，把老公养成了儿子","":"","imgUrl":"https://upload-images.jianshu.io/upload_images/18529263-c8f3a44e0cebe8a2?imageMogr2/auto-orient/strip|imageView2/1/w/150/h/120","abstract":"文 | 小绿也 这两天，我在看综艺《我家小两口》。 在三对夫妻中，严屹宽和妻子杜若溪是结婚时间最长的一对，在一起10年，结婚5年，有个1岁的女儿...","meta":"543","author":"S小姐说","meta2":"98","meta3":""},
      {"title":"“我妈昨晚走了，到死也没见过大海”","":"","imgUrl":"","abstract":"01 刷朋友圈，忽然看到同学小麦发了一条： “老妈昨晚走了，到死也没看过大海。” 我心里一惊，也一酸，赶紧发私信安慰她。 几天后，她拨了语音通话...","meta":"59","author":"S小姐说","meta2":"22","meta3":"3"},
      {"title":"16岁拍裸体写真，19岁拍三级片，29岁获影后，如今成最大赢家","":"","imgUrl":"https://upload-images.jianshu.io/upload_images/1216164-45d121d646516027.jpg?imageMogr2/auto-orient/strip|imageView2/1/w/150/h/120","abstract":"舒淇，何许人也？ 16岁被星探发掘拍裸体写真，19岁接拍三级片进入大众视野，20岁走在大街上被人大喊“脱星”。 年少成名，被贴上“艳星”标签， ...","meta":"167.7","author":"孔南词","meta2":"216","meta3":"1258"},
      {"title":"年少不懂张无忌，读懂已是负心人","":"","imgUrl":"https://upload-images.jianshu.io/upload_images/18529254-bb420f8908ab0d3c?imageMogr2/auto-orient/strip|imageView2/1/w/150/h/120","abstract":"《倚天屠龙记》又翻拍了。 新版最大的槽点，是慢动作拖剧情、选角网红脸化。 但也有个很大的看点：多年前，周海媚贡献了一版最经典的周芷若，没想到如今...","meta":"55","author":"書酱","meta2":"16","meta3":""},
      {"title":"杨紫，你真的该火了！","":"","imgUrl":"https://upload-images.jianshu.io/upload_images/18529255-f36ca427edcce7fa?imageMogr2/auto-orient/strip|imageView2/1/w/150/h/120","abstract":"娱乐圈有这样一朵小花，她没有惊天的颜值，没有吓死人的背景，看起来普普通通，演技却让人心服口服。 你已经猜到了，没错，我说的就是杨紫。 最近，杨紫...","meta":"421","author":"热心市民顾先生","meta2":"60","meta3":""},
      {"title":"黄晓明的“黄氏自信”到底是哪来的？摆脱了油腻却迎来了中年王子病","":"","imgUrl":"https://upload-images.jianshu.io/upload_images/18529263-3aa2ab9871b6f298?imageMogr2/auto-orient/strip|imageView2/1/w/150/h/120","abstract":"黄晓明招黑也不是一天两天的了，早年一句“闹太套”就被全国人民嘲了好几年。 今年又因为一档《中餐厅3》在节目里黄店长霸道的一言一行被全网暴骂！店长...","meta":"48","author":"S小姐说","meta2":"6","meta3":""},
      {"title":"51岁张敏近照曝光，依旧美艳动人，终于说出当年不嫁周星驰的真相","":"","imgUrl":"https://upload-images.jianshu.io/upload_images/2259045-a5ce164174681783?imageMogr2/auto-orient/strip|imageView2/1/w/150/h/120","abstract":"文/麦大人 01 许多年以后，我们一直念念不忘黄金时代的香港电影，以及旧时光里的那些美人，评选出了几个最让人难忘的经典镜头。 最广为人知的有四个...","meta":"219.5","author":"麦大人","meta2":"111","meta3":"567"},
      {"title":"嫁给一个这样的男人，有多煎熬","":"","imgUrl":"","abstract":"燕子是我的高中同学，她说最近她被老公气得要抑郁了，不知道该怎么办?谈离婚吧，也许不至于，不离吧，咽不下那口气。冷战了十几天了。 那天老公跟她大吵...","meta":"78.0","author":"ZW微风和煦","meta2":"162","meta3":"263"},
      {"title":"深圳女孩独游华山遇害：原本她有两次活命的机会","":"","imgUrl":"https://upload-images.jianshu.io/upload_images/18529263-3d0e487a463e8ec8?imageMogr2/auto-orient/strip|imageView2/1/w/150/h/120","abstract":"文 | 富书乔巴  来源 | 富书（ID：kolfrc） 01 生命的凋零比想象中更容易 昨天看到一条很沉重的新闻。 27岁深圳女孩彭雯7月16...","meta":"587","author":"S小姐说","meta2":"170","meta3":"1"},
      {"title":"9岁女孩常用假币买水果，水果店主跟踪回家，看到躺在床上的人蒙了","":"","imgUrl":"","abstract":"李三元在市里经营几家水果店。最近李三元在巡视店铺时，发现一个陌生小女孩总是拿10元假币来买一两个水果，起疑的他跟踪小女孩，却无意中收获了梦寐以求...","meta":"86.2","author":"猫哥聊社会","meta2":"75","meta3":"496"},
      {"title":"海清公开为自己求好处，真丑！","":"","imgUrl":"https://upload-images.jianshu.io/upload_images/1016328-6a13fb2297107c34?imageMogr2/auto-orient/strip|imageView2/1/w/150/h/120","abstract":"以一群人的身份自居，那你就要为一群人的利益着想，但到了海清那里就成了为自己求好处。 文 | 小义 来源 | 小义了不休（ID：rxiaoyi23...","meta":"70.8","author":"小义23","meta2":"192","meta3":"240"},
      {"title":"卖了100贝，头一次见这么多钱！","":"","imgUrl":"https://upload-images.jianshu.io/upload_images/10232737-7b1117edc45b0c70.jpg?imageMogr2/auto-orient/strip|imageView2/1/w/150/h/120","abstract":"眼瞅着好多简友卖贝发了财，我也来尝尝鲜。今天在贝市场卖了100贝，忘截图了。交易显示成功，但问题是钱跑哪去了？ 在“我的钱包”里没找到钱，难道被...","meta":"221.2","author":"金错刀618","meta2":"210","meta3":"1053"},
      {"title":"小米美女总监贪700万被抓：最可怕的，是在欲望的路上裸奔","":"","imgUrl":"https://upload-images.jianshu.io/upload_images/18529254-2d438ce82c7a2afd?imageMogr2/auto-orient/strip|imageView2/1/w/150/h/120","abstract":"01 最可怕的 是在欲望的路上裸奔 最近看到一个新闻，蛮痛心的。 7月20日，小米发布内部邮件，通报称： 公司2名员工涉嫌贪腐，已经被公司辞退。...","meta":"719","author":"書酱","meta2":"127","meta3":"2"},
      {"title":"深圳纪事（8）：离职华为","":"","imgUrl":"","abstract":"2016年6月，儿子跟我说，他想从华为离职。 我很吃惊，问：“为何？上班路又不远，待遇又不低。” 他说：“原来每周加班三天，我忍受三年了，现在加...","meta":"248.9","author":"文孤子","meta2":"250","meta3":"1022"},
      {"title":"任达华被刺在群里求助：成年人的生活，谁不是人前逞强，人后投降","":"","imgUrl":"https://upload-images.jianshu.io/upload_images/2311657-1dd225dea331176c?imageMogr2/auto-orient/strip|imageView2/1/w/150/h/120","abstract":"01. 昨天，参加商业活动的任达华，被突然闯上台的男子刺伤，瞬间成为爆炸新闻。 画面中，我们可以看到，不知情的任达华，以为男子是上台打招呼的，还...","meta":"187.4","author":"S的魔镜","meta2":"108","meta3":"986"},
      {"title":"一场直播事故，掀开了直播界阴暗黑幕的一角","":"","imgUrl":"https://upload-images.jianshu.io/upload_images/15732823-01615b8e82b841ad?imageMogr2/auto-orient/strip|imageView2/1/w/150/h/120","abstract":"一场直播事故，占据了各大网络平台热搜。 7月25日，一个从未露过脸的萝莉主播（萝莉一般指8-12岁小女孩），由于某种原因，一不小心漏了脸。这不漏...","meta":"152.2","author":"Link_be41","meta2":"156","meta3":"835"},
      {"title":"卖不掉的房子，被套在北京的我们","":"","imgUrl":"https://upload-images.jianshu.io/upload_images/9275049-656172428dcefd3e.jpg?imageMogr2/auto-orient/strip|imageView2/1/w/150/h/120","abstract":"从武汉开往北京的高铁上，我和老公一直在搜索“商住房”的消息。几乎所有的热点文章，都将商办类房产贬得一文不值。那些“预计价格将下跌30%，成交量下...","meta":"130.7","author":"网易人间","meta2":"127","meta3":"672"}
      
      ],
    "recommendList": [
      {
        "id": 1,
        "imgUrl": "http://cdn2.jianshu.io/assets/web/banner-s-club-aa8bdf19f8cf729a759da42e4a96f366.png"
      },
      {
        "id": 2,
        "imgUrl": "http://cdn2.jianshu.io/assets/web/banner-s-7-1a0222c91694a1f38e610be4bf9669be.png"
      },
      {
        "id": 3,
        "imgUrl": "http://cdn2.jianshu.io/assets/web/banner-s-5-4ba25cf5041931a0ed2062828b4064cb.png"
      },
      {
        "id": 4,
        "imgUrl": "http://cdn2.jianshu.io/assets/web/banner-s-6-c4d6335bfd688f2ca1115b42b04c28a7.png"
      }
    ]
  }
}